{
  "huespedes": [
    {
      "_id": 1,
      "tipodoc": "Cédula de ciudadanía",
      "numdoc": "1234567890",
      "nombre": "Pepito Andrés",
      "apellido": "Perez Valvuena",
      "fnacimiento": "1996-06-24T00:00:00.000Z",
      "genero": "Masculino",
      "email": "pepito@mail.com",
      "telefono": "3193780293",
      "paisorigen": "Colombia",
      "password": "Nueva123",
      "tipouser": "Huésped",
      "img": "",
      "reservas": [],
      "__v": 3
    },
    {
      "_id": 2,
      "tipodoc": "Cédula de ciudadanía",
      "numdoc": 1234567891,
      "nombre": "Fulana",
      "apellido": "Lopez",
      "fnacimiento": "1996-09-30T00:00:00.000Z",
      "genero": "Femenino",
      "email": "fulana@mail.com",
      "telefono": 3132693652,
      "paisorigen": "Colombia",
      "password": "Pruebas124*",
      "tipouser": "Huésped",
      "img": "",
      "reservas": [],
      "__v": 3
    },
    {
      "_id": 3,
      "tipodoc": "Cédula de ciudadanía",
      "numdoc": 1234567893,
      "nombre": "Sabin",
      "apellido": "Lopez",
      "fnacimiento": "1996-09-30T00:00:00.000Z",
      "genero": "Femenino",
      "email": "sabin@mail.com",
      "telefono": 3173902876,
      "paisorigen": "Colombia",
      "password": "Pruebas125*",
      "tipouser": "Huésped",
      "img": "",
      "reservas": [],
      "__v": 3
    },
    {
      "_id": 1234567890,
      "tipodoc": "Cédula de ciudadanía",
      "nombre": "Mario Alberto",
      "apellido": "Yepes Caicedo",
      "fnacimiento": "1982-06-25T00:00:00.000Z",
      "genero": "femenino",
      "email": "marioyepes@gmail.com",
      "telefono": "3123456789",
      "paisorigen": "Colombia",
      "password": "qwerty",
      "tipouser": "administrador",
      "img": "",
      "reservas": [],
      "__v": 3
      }
  ],

  "habitaciones":[
    {
      "_id": 101,
      "nombrehab": "Suite Deluxe",
      "capacidad": 3,
      "camas": "2",
      "descripcion": "2 camas 1 doble 1 sencilla, baño privado",
      "wifi": "si",
      "tv": "si",
      "banio": "si",
      "cajafuerte": "si",
      "nevera": "si",
      "valornoche": 125000,
      "img": "",
      "estado": "Disponible",
      "reservas": [
      {
      "_id": "62d0ca485d2107d3fb8595de",
      "fentrada": "2022-07-16T00:00:00.000Z",
      "fsalida": "2022-07-18T00:00:00.000Z",
      "cantidadNoches": 2,
      "freserva": "2022-07-15T02:00:40.825Z",
      "totalreserva": 200000
      },
      {
      "_id": "62d0d05081d738cacdacd186",
      "fentrada": "2022-07-20T00:00:00.000Z",
      "fsalida": "2022-07-23T00:00:00.000Z",
      "cantidadNoches": 3,
      "freserva": "2022-07-15T02:26:24.555Z",
      "totalreserva": 375000
      }
      ],
      "__v": 2
    },
    {
      "_id": 102,
      "nombrehab": "Swete Básica",
      "capacidad": 2,
      "camas": "1",
      "descripcion": "1 cama dole baño privado",
      "wifi": "si",
      "tv": "si",
      "banio": "si",
      "cajafuerte": "si",
      "nevera": "si",
      "valornoche": 100000,
      "estado": "disponible",
      "img": "",
      "__v": 1,
      "reservas": [
      {
      "_id": "62d15e0702ec9b90d829dca6",
      "fentrada": "2022-07-27T00:00:00.000Z",
      "fsalida": "2022-07-29T00:00:00.000Z",
      "cantidadNoches": 2,
      "freserva": "2022-07-15T12:31:03.648Z",
      "totalreserva": 200000
      }
      ]
    },
    {
      "_id": 1,
      "nombrehab": "Habitación 1A",
      "capacidad": 4,
      "camas": "3",
      "descripcion": "Lorem ipsum dolor sit amet, consectetur adipiscing elit, sed do eiusmod tempor incididunt ut labore et dolore magna aliqua.",
      "wifi": "si",
      "tv": "si",
      "banio": "si",
      "cajafuerte": "no",
      "nevera": "no",
      "valornoche": 160000,
      "estado": "disponible",
      "img": "",
      "__v": 1,
      "reservas": []
    },
    {
      "_id": 2,
      "nombrehab": "Habitación 2A",
      "capacidad": 2,
      "camas": "4",
      "descripcion": "Lorem ipsum dolor sit amet, consectetur adipiscing elit, sed do eiusmod tempor incididunt ut labore et dolore magna aliqua.",
      "wifi": "si",
      "tv": "si",
      "banio": "si",
      "cajafuerte": "si",
      "nevera": "si",
      "valornoche": 180000,
      "estado": "disponible",
      "img": "",
      "__v": 1,
      "reservas": []
    },
    {
      "_id": 3,
      "nombrehab": "Habitación 3A",
      "capacidad": 10,
      "camas": "5",
      "descripcion": "Lorem ipsum dolor sit amet, consectetur adipiscing elit, sed do eiusmod tempor incididunt ut labore et dolore magna aliqua.",
      "wifi": "si",
      "tv": "si",
      "banio": "si",
      "cajafuerte": "no",
      "nevera": "si",
      "valornoche": 210000,
      "estado": "disponible",
      "img": "",
      "__v": 1,
      "reservas": []
    },
    {
      "_id": 4,
      "nombrehab": "Habitación 4A",
      "capacidad": 2,
      "camas": "1",
      "descripcion": "Lorem ipsum dolor sit amet, consectetur adipiscing elit, sed do eiusmod tempor incididunt ut labore et dolore magna aliqua.",
      "wifi": "si",
      "tv": "si",
      "banio": "si",
      "cajafuerte": "no",
      "nevera": "no",
      "valornoche": 140000,
      "estado": "disponible",
      "img": "",
      "__v": 1,
      "reservas": []
    },
    {
      "_id": 5,
      "nombrehab": "Habitación 5B",
      "capacidad": 6,
      "camas": "3",
      "descripcion": "Lorem ipsum dolor sit amet, consectetur adipiscing elit, sed do eiusmod tempor incididunt ut labore et dolore magna aliqua.",
      "wifi": "si",
      "tv": "si",
      "banio": "si",
      "cajafuerte": "no",
      "nevera": "si",
      "valornoche": 210000,
      "estado": "disponible",
      "img": "",
      "__v": 1,
      "reservas": []
    },
    {
      "_id": 6,
      "nombrehab": "Habitación 6B",
      "capacidad": 8,
      "camas": "4",
      "descripcion": "Lorem ipsum dolor sit amet, consectetur adipiscing elit, sed do eiusmod tempor incididunt ut labore et dolore magna aliqua.",
      "wifi": "si",
      "tv": "si",
      "banio": "si",
      "cajafuerte": "no",
      "nevera": "si",
      "valornoche": 220000,
      "estado": "disponible",
      "img": "",
      "__v": 1,
      "reservas": []
    },
    {
      "_id": 7,
      "nombrehab": "Habitación 7B",
      "capacidad": 4,
      "camas": "2",
      "descripcion": "Lorem ipsum dolor sit amet, consectetur adipiscing elit, sed do eiusmod tempor incididunt ut labore et dolore magna aliqua.",
      "wifi": "si",
      "tv": "si",
      "banio": "si",
      "cajafuerte": "no",
      "nevera": "no",
      "valornoche": 180000,
      "estado": "No disponible",
      "img": "",
      "__v": 1,
      "reservas": []
    },
    {
      "_id": 8,
      "nombrehab": "Habitación 8B",
      "capacidad": 6,
      "camas": "3",
      "descripcion": "Lorem ipsum dolor sit amet, consectetur adipiscing elit, sed do eiusmod tempor incididunt ut labore et dolore magna aliqua.",
      "wifi": "si",
      "tv": "si",
      "banio": "si",
      "cajafuerte": "no",
      "nevera": "no",
      "valornoche": 200000,
      "estado": "No disponible",
      "img": "",
      "__v": 1,
      "reservas": []
    }
  ]
}